LICENSE
README.md
setup.py
src/deploy/__init__.py
src/deploy/commands.py
src/deploy/deploy.py
src/deploy/ecr.py
src/deploy/ecs.py
src/deploy/exceptions.py
src/deploy/git.py
src/deploy/iam.py
src/deploy/iterators.py
src/deploy/models.py
src/deploy/pretty_printing.py
src/deploy/project.py
src/deploy/release_store.py
src/deploy/tags.py
src/deploy/version.py
src/deploy/version_check.py
src/weco_deploy.egg-info/PKG-INFO
src/weco_deploy.egg-info/SOURCES.txt
src/weco_deploy.egg-info/dependency_links.txt
src/weco_deploy.egg-info/entry_points.txt
src/weco_deploy.egg-info/requires.txt
src/weco_deploy.egg-info/top_level.txt